[
  {
    "data": [
      {
        "id": "MARAD-2002-12977-0001",
        "type": "documents",
        "attributes": {
          "documentType": "Rule",
          "lastModifiedDate": "2008-01-08T20:01:39Z",
          "highlightedContent": "",
          "frDocNum": null,
          "withdrawn": false,
          "agencyId": "MARAD",
          "commentEndDate": "2002-08-03T03:59:59Z",
          "title": "U.S. DOT/MARAD - Invitation for public comments on a requested administrative waiver of the Coastwise Trade Laws for the vessel STEPHANIE ANN",
          "postedDate": "2002-08-02T04:00:00Z",
          "docketId": "MARAD-2002-12977",
          "subtype": "Federal Register Publication",
          "commentStartDate": "2002-08-02T04:00:00Z",
          "openForComment": false,
          "objectId": "0900006480307ea6"
        },
        "links": {
          "self": "https://api.regulations.gov/v4/documents/MARAD-2002-12977-0001"
        }
      },
      {
        "id": "USCG-2002-12927-0001",
        "type": "documents",
        "attributes": {
          "documentType": "Rule",
          "lastModifiedDate": "2017-03-10T22:18:28Z",
          "highlightedContent": "",
          "frDocNum": null,
          "withdrawn": false,
          "agencyId": "USCG",
          "commentEndDate": "2002-08-03T03:59:59Z",
          "title": "Notice of Meetings",
          "postedDate": "2002-08-02T04:00:00Z",
          "docketId": "USCG-2002-12927",
          "subtype": "Federal Register Publication",
          "commentStartDate": "2002-08-02T04:00:00Z",
          "openForComment": false,
          "objectId": "0900006480307d35"
        },
        "links": {
          "self": "https://api.regulations.gov/v4/documents/USCG-2002-12927-0001"
        }
      },
      {
        "id": "MARAD-2002-12842-0001-0001",
        "type": "documents",
        "attributes": {
          "documentType": "Rule",
          "lastModifiedDate": "2008-01-08T20:01:59Z",
          "highlightedContent": "",
          "frDocNum": null,
          "withdrawn": false,
          "agencyId": "MARAD",
          "commentEndDate": "2002-08-03T03:59:59Z",
          "title": "U.S. DOT/MARAD - Policy Review with Request for Comments",
          "postedDate": "2002-08-02T04:00:00Z",
          "docketId": "MARAD-2002-12842",
          "subtype": "Federal Register Publication",
          "commentStartDate": "2002-08-02T04:00:00Z",
          "openForComment": false,
          "objectId": "0900006480307a48"
        },
        "links": {
          "self": "https://api.regulations.gov/v4/documents/MARAD-2002-12842-0001-0001"
        }
      },
      {
        "id": "NRC-2002-0011-0012",
        "type": "documents",
        "attributes": {
          "documentType": "Proposed Rule",
          "lastModifiedDate": "2022-04-21T01:00:47Z",
          "highlightedContent": "",
          "frDocNum": null,
          "withdrawn": false,
          "agencyId": "NRC",
          "commentEndDate": "2002-10-17T03:59:59Z",
          "title": "Federal Register Notice - Proposed Rule:  Combustible Gas Control in Containment",
          "postedDate": "2002-08-02T19:11:58Z",
          "docketId": "NRC-2002-0011",
          "subtype": null,
          "commentStartDate": "2002-08-02T19:11:58Z",
          "openForComment": false,
          "objectId": "090000648054c6c9"
        },
        "links": {
          "self": "https://api.regulations.gov/v4/documents/NRC-2002-0011-0012"
        }
      },
      {
        "id": "NHTSA-2002-11882-0002",
        "type": "documents",
        "attributes": {
          "documentType": "Rule",
          "lastModifiedDate": "2008-01-08T20:14:53Z",
          "highlightedContent": "",
          "frDocNum": null,
          "withdrawn": false,
          "agencyId": "NHTSA",
          "commentEndDate": "2002-08-03T03:59:59Z",
          "title": "U.S. DOT/NHTSA - Michelin North America, Inc., Grant of Application for Decision",
          "postedDate": "2002-08-02T04:00:00Z",
          "docketId": "NHTSA-2002-11882",
          "subtype": "Federal Register Publication",
          "commentStartDate": "2002-08-02T04:00:00Z",
          "openForComment": false,
          "objectId": "0900006480305412"
        },
        "links": {
          "self": "https://api.regulations.gov/v4/documents/NHTSA-2002-11882-0002"
        }
      },
      {
        "id": "MARAD-2002-12978-0001",
        "type": "documents",
        "attributes": {
          "documentType": "Rule",
          "lastModifiedDate": "2008-01-08T20:01:58Z",
          "highlightedContent": "",
          "frDocNum": null,
          "withdrawn": false,
          "agencyId": "MARAD",
          "commentEndDate": "2002-08-03T03:59:59Z",
          "title": "U.S. DOT/MARAD - Invitation for public comments on a requested administrative waiver of the Coastwise Trade Laws for the vessel FANTASIA",
          "postedDate": "2002-08-02T04:00:00Z",
          "docketId": "MARAD-2002-12978",
          "subtype": "Federal Register Publication",
          "commentStartDate": "2002-08-02T04:00:00Z",
          "openForComment": false,
          "objectId": "0900006480307eb2"
        },
        "links": {
          "self": "https://api.regulations.gov/v4/documents/MARAD-2002-12978-0001"
        }
      },
      {
        "id": "USCG-2002-12916-0001",
        "type": "documents",
        "attributes": {
          "documentType": "Rule",
          "lastModifiedDate": "2017-03-10T22:18:28Z",
          "highlightedContent": "",
          "frDocNum": null,
          "withdrawn": false,
          "agencyId": "USCG",
          "commentEndDate": "2002-08-03T03:59:59Z",
          "title": "U.S. DOT/USCG - Request for Applications",
          "postedDate": "2002-08-02T04:00:00Z",
          "docketId": "USCG-2002-12916",
          "subtype": "Federal Register Publication",
          "commentStartDate": "2002-08-02T04:00:00Z",
          "openForComment": false,
          "objectId": "0900006480307cd6"
        },
        "links": {
          "self": "https://api.regulations.gov/v4/documents/USCG-2002-12916-0001"
        }
      },
      {
        "id": "MARAD-2002-12725-0003",
        "type": "documents",
        "attributes": {
          "documentType": "Rule",
          "lastModifiedDate": "2008-01-08T20:02:47Z",
          "highlightedContent": "",
          "frDocNum": null,
          "withdrawn": false,
          "agencyId": "MARAD",
          "commentEndDate": "2002-08-03T03:59:59Z",
          "title": "U.S. DOT/MARAD - Invitation for public comments on a requested administrative waiver of the Coastwise Trade Laws for the vessel THORR with expanded geographic area of operation",
          "postedDate": "2002-08-02T04:00:00Z",
          "docketId": "MARAD-2002-12725",
          "subtype": "Federal Register Publication",
          "commentStartDate": "2002-08-02T04:00:00Z",
          "openForComment": false,
          "objectId": "090000648030761d"
        },
        "links": {
          "self": "https://api.regulations.gov/v4/documents/MARAD-2002-12725-0003"
        }
      },
      {
        "id": "MARAD-2002-12842-0001-0002",
        "type": "documents",
        "attributes": {
          "documentType": "Rule",
          "lastModifiedDate": "2008-01-08T20:02:47Z",
          "highlightedContent": "",
          "frDocNum": null,
          "withdrawn": false,
          "agencyId": "MARAD",
          "commentEndDate": "2002-08-03T03:59:59Z",
          "title": "U.S. DOT/MARAD - Policy Review with Request for Comments",
          "postedDate": "2002-08-02T04:00:00Z",
          "docketId": "MARAD-2002-12842",
          "subtype": "Federal Register Publication",
          "commentStartDate": "2002-08-02T04:00:00Z",
          "openForComment": false,
          "objectId": "0900006480307a49"
        },
        "links": {
          "self": "https://api.regulations.gov/v4/documents/MARAD-2002-12842-0001-0002"
        }
      },
      {
        "id": "FAA-2002-12534-0002",
        "type": "documents",
        "attributes": {
          "documentType": "Rule",
          "lastModifiedDate": "2008-01-12T00:38:26Z",
          "highlightedContent": "",
          "frDocNum": null,
          "withdrawn": false,
          "agencyId": "FAA",
          "commentEndDate": "2002-08-03T03:59:59Z",
          "title": "U.S. DOT/FAA - Notice of Petitions for Exemption Received",
          "postedDate": "2002-08-02T04:00:00Z",
          "docketId": "FAA-2002-12534",
          "subtype": "Federal Register Publication",
          "commentStartDate": "2002-08-02T04:00:00Z",
          "openForComment": false,
          "objectId": "0900006480307010"
        },
        "links": {
          "self": "https://api.regulations.gov/v4/documents/FAA-2002-12534-0002"
        }
      }
    ],
    "meta": {
      "aggregations": {
        "documentType": [
          {
            "docCount": 121,
            "label": "Other"
          },
          {
            "docCount": 9,
            "label": "Rule"
          },
          {
            "docCount": 5,
            "label": "Notice"
          },
          {
            "docCount": 4,
            "label": "Supporting & Related Material"
          },
          {
            "docCount": 1,
            "label": "Proposed Rule"
          }
        ],
        "subtype": [
          {
            "docCount": 9,
            "label": "Federal Register Publication"
          }
        ],
        "withinCommentPeriod": [
          {
            "docCount": 0,
            "label": "true"
          },
          {
            "docCount": 10,
            "label": "false"
          }
        ],
        "agencyId": [
          {
            "docCount": 5,
            "value": "MARAD"
          },
          {
            "docCount": 2,
            "value": "USCG"
          },
          {
            "docCount": 1,
            "value": "FAA"
          },
          {
            "docCount": 1,
            "value": "NHTSA"
          },
          {
            "docCount": 1,
            "value": "NRC"
          }
        ],
        "commentEndDate": [],
        "postedDate": [
          {
            "docCount": 106,
            "label": "Last 7 Days",
            "fromDate": "2023-08-22 00:00:00",
            "toDate": "2023-08-28 23:59:59"
          },
          {
            "docCount": 257,
            "label": "Last 15 Days",
            "fromDate": "2023-08-14 00:00:00",
            "toDate": "2023-08-28 23:59:59"
          },
          {
            "docCount": 482,
            "label": "Last 30 Days",
            "fromDate": "2023-07-30 00:00:00",
            "toDate": "2023-08-28 23:59:59"
          },
          {
            "docCount": 1393,
            "label": "Last 90 Days",
            "fromDate": "2023-05-31 00:00:00",
            "toDate": "2023-08-28 23:59:59"
          }
        ]
      },
      "filters": {
        "postedDate": {
          "fromDate": "2002-08-02",
          "toDate": "2002-08-02"
        },
        "documentType": [
          {
            "label": "Proposed Rule",
            "value": "Proposed Rule"
          },
          {
            "label": "Rule",
            "value": "Rule"
          }
        ]
      },
      "hasNextPage": false,
      "hasPreviousPage": false,
      "numberOfElements": 10,
      "pageNumber": 1,
      "pageSize": 250,
      "totalElements": 10,
      "totalPages": 1,
      "firstPage": true,
      "lastPage": true
    }
  }
]